your/__init__.py
your/candidate.py
your/writer.py
your/your.py
your/formats/__init__.py
your/formats/dada.py
your/formats/filwriter.py
your/formats/fitswriter.py
your/formats/psrfits.py
your/formats/pysigproc.py
your/utils/__init__.py
your/utils/astro.py
your/utils/gpu.py
your/utils/heimdall.py
your/utils/math.py
your/utils/misc.py
your/utils/plotter.py
your/utils/rfi.py
your-0.6.7.data/scripts/your_bandpass.py
your-0.6.7.data/scripts/your_candmaker.py
your-0.6.7.data/scripts/your_combine_mocks.py
your-0.6.7.data/scripts/your_h5plotter.py
your-0.6.7.data/scripts/your_header.py
your-0.6.7.data/scripts/your_heimdall.py
your-0.6.7.data/scripts/your_rfimask.py
your-0.6.7.data/scripts/your_viewer.py
your-0.6.7.data/scripts/your_writer.py
your-0.6.7.dist-info/LICENSE
your-0.6.7.dist-info/METADATA
your-0.6.7.dist-info/WHEEL
your-0.6.7.dist-info/top_level.txt
your-0.6.7.dist-info/RECORD
