Metadata-Version: 2.1
Name: your
Version: 0.6.7
Summary: A unified reader for sigproc filterbank and psrfits data
Home-page: https://github.com/thepetabyteproject/your
Author: Devansh Agarwal, Kshitij Aggarwal
Author-email: da0017@mix.wvu.edu, ka0064@mix.wvu.edu
License: UNKNOWN
Platform: UNKNOWN
Classifier: Natural Language :: English
Classifier: Intended Audience :: Science/Research
Classifier: Programming Language :: Python
Classifier: Programming Language :: Python :: 3
Classifier: Programming Language :: Python :: 3.6
Classifier: Programming Language :: Python :: 3.7
Classifier: Programming Language :: Python :: 3.8
Classifier: Programming Language :: Python :: 3.9
Classifier: License :: OSI Approved :: GNU General Public License v3 (GPLv3)
Classifier: Topic :: Scientific/Engineering :: Astronomy
Requires-Dist: matplotlib (>=3.2.1)
Requires-Dist: numpy (>=1.18.4)
Requires-Dist: h5py (>=2.10.0)
Requires-Dist: scikit-image (>=0.14.2)
Requires-Dist: scipy (>=1.3.0)
Requires-Dist: numba (>=0.48.0)
Requires-Dist: astropy (>=4.0)
Requires-Dist: pandas (>=1.0.3)
Requires-Dist: rich (>=8.0)
